knnn/__init__.py
knnn/knnn_classification.py
knnn/knnn_main.py
knnn/utils.py
tests/__init__.py
tests/test_1_knnn_basics.py
tests/test_2_knnn_synthetic_dataset_creation.py
tests/test_3_knnn_results_synthetic.py
tests/test_4_knnn_results_real.py
tests/test_5_knnn_results_real_ADB.py
tests/utils.py
knnn-0.0.9.dist-info/METADATA
knnn-0.0.9.dist-info/WHEEL
knnn-0.0.9.dist-info/top_level.txt
knnn-0.0.9.dist-info/RECORD
