Metadata-Version: 2.4
Name: knnn
Version: 0.0.9
Summary: An implementation of KNNN algorithm
Home-page: https://github.com/onr/knnn
Author: Ori Nizan
Author-email: restin3@gmail.com
Project-URL: Homepage, https://github.com/onr/knnn
Project-URL: Bug Tracker, https://github.com/onr/knnn/issues
Keywords: knnn,knn,embedding
Classifier: Programming Language :: Python :: 3
Classifier: License :: OSI Approved :: MIT License
Classifier: Operating System :: OS Independent
Requires-Python: >=3.7
Requires-Dist: numpy
Requires-Dist: scipy
Requires-Dist: tqdm
Requires-Dist: faiss-cpu
Provides-Extra: tests
Requires-Dist: pytest; extra == "tests"
Requires-Dist: datasets; extra == "tests"
Requires-Dist: pandas; extra == "tests"
Requires-Dist: faiss-gpu; extra == "tests"
Provides-Extra: faiss-gpu
Requires-Dist: faiss-gpu; extra == "faiss-gpu"
Dynamic: author
Dynamic: author-email
Dynamic: classifier
Dynamic: description
Dynamic: description-content-type
Dynamic: home-page
Dynamic: keywords
Dynamic: project-url
Dynamic: provides-extra
Dynamic: requires-dist
Dynamic: requires-python
Dynamic: summary
